MANIFEST.in
README.rst
ds-down.conf
ds-down.desktop
setup.cfg
setup.py
src/ds_down.egg-info/PKG-INFO
src/ds_down.egg-info/SOURCES.txt
src/ds_down.egg-info/dependency_links.txt
src/ds_down.egg-info/entry_points.txt
src/ds_down.egg-info/not-zip-safe
src/ds_down.egg-info/top_level.txt
src/wor/__init__.py
src/wor/ds_down.py