Metadata-Version: 1.1
Name: ds-down
Version: 0.2.1
Summary: Synology Download Station url adder.
Home-page: http://github.com/wor/ds-down
Author: Esa Määttä
Author-email: esa.maatta@iki.fi
License: GPL3
Keywords: Synology DownloadStation console cli
Platform: UNKNOWN
Classifier: Development Status :: 4 - Beta
Classifier: License :: OSI Approved :: GNU General Public License v3 or later (GPLv3+)
Classifier: Environment :: Console
Classifier: Programming Language :: Python :: 3
Classifier: Operating System :: POSIX :: Linux
Classifier: Topic :: Utilities
